README.txt
setup.cfg
setup.py
thrift3babeltrace/TMultiplexedProcessor.py
thrift3babeltrace/TSCons.py
thrift3babeltrace/TSerialization.py
thrift3babeltrace/TTornado.py
thrift3babeltrace/Thrift.py
thrift3babeltrace/__init__.py
thrift3babeltrace.egg-info/PKG-INFO
thrift3babeltrace.egg-info/SOURCES.txt
thrift3babeltrace.egg-info/dependency_links.txt
thrift3babeltrace.egg-info/top_level.txt
thrift3babeltrace/protocol/TBase.py
thrift3babeltrace/protocol/TBinaryProtocol.py
thrift3babeltrace/protocol/TCompactProtocol.py
thrift3babeltrace/protocol/TJSONProtocol.py
thrift3babeltrace/protocol/TMultiplexedProtocol.py
thrift3babeltrace/protocol/TProtocol.py
thrift3babeltrace/protocol/TProtocolDecorator.py
thrift3babeltrace/protocol/__init__.py
thrift3babeltrace/server/THttpServer.py
thrift3babeltrace/server/TNonblockingServer.py
thrift3babeltrace/server/TProcessPoolServer.py
thrift3babeltrace/server/TServer.py
thrift3babeltrace/server/__init__.py
thrift3babeltrace/transport/THttpClient.py
thrift3babeltrace/transport/TSSLSocket.py
thrift3babeltrace/transport/TSocket.py
thrift3babeltrace/transport/TTransport.py
thrift3babeltrace/transport/TTwisted.py
thrift3babeltrace/transport/TZlibTransport.py
thrift3babeltrace/transport/__init__.py