Metadata-Version: 1.1
Name: thrift3babeltrace
Version: 0.2.2
Summary: Apache Thrift with modifications for compatibility for Python 3
Home-page: https://github.com/vears91/thrift3-binary-protocol
Author: Victor Araujo
Author-email: ve.ar91@gmail.com
License: UNKNOWN
Download-URL: https://github.com/vears91/thrift3-binary-protocol/tarball/0.2.1
Keywords: thrift,python3,binary protocol,thrift3,babeltrace
Platform: UNKNOWN
